{
    "Restaurants": [
        {
            "Restaurant": "Tikka House",
            "Restaurant-Mission": "To bring joy throughout the world, one bowl at a time",
            "Brand-Phrase": "Fresh curry, warm naan, happy families",
            "Group": "a part of the DRG Family",
            "Menu-Item-1": "Chicken Tikka Masala",
            "Menu-Item-2": "Chicken Makhani",
            "Menu-Item-3": "Lamb Biriyani",
            "Menu-Item-4": "Goat Korma",
            "Menu-Item-1-price": 12.99,
            "Menu-Item-2-price": 11.99,
            "Menu-Item-3-price": 15.99,
            "Menu-Item-4-price": 14.99,
            "Menu-Item-1-description": "Toasted and warmed spices in a tangy tomato gravy",
            "Menu-Item-2-description": "Creamy and decadent gravy with a velvetty texture",
            "Menu-Item-3-description": "A traditional rice dish with succulent lamb interleaved with rice, saffron milk, and spices",
            "Menu-Item-4-description": "A beloved meat of India with coconut milk based gravy"
        },
        {
            "Restaurant": "Martes de Tacos",
            "Restaurant-Mission": "We will make taco tuesday every day of the week",
            "Brand-Phrase": "Tacos should not be 4 dollars,but they should taste as such. That is where we come in.",
            "Group": "a part of the DRG Family",
            "Menu-Item-1": "Tacos (Al Pastor, Carne Asada, Chorizo)",
            "Menu-Item-2": "Burritos (Carne Asada, Vegetarian,Chicken Tinga)",
            "Menu-Item-3": "Mexicanas (Al Pastor)",
            "Menu-Item-4": "Gringas (Al Pastor)",
            "Menu-Item-1-price": 2.00,
            "Menu-Item-2-price": 8.99,
            "Menu-Item-3-price": 2.50,
            "Menu-Item-4-price": 2.50,
            "Menu-Item-1-description": "Tacos wrapped in fresh corn tortillas, onion, cilantro, and your choice of meat",
            "Menu-Item-2-description": "Burritos served with beans, guacamole, pico. rice or fries if California style",
            "Menu-Item-3-description": "Everything that comes in a taco, but with griddled and melted queso oaxaca.",
            "Menu-Item-4-description": "Everything that comes in a taco, on a flour tortilla, griddled and melted spicy monterry jack cheese"
        },
        {
            "Restaurant": "Lo stivale",
            "Restaurant-Mission": "To create a fresh wholesome experience unico in Italia",
            "Brand-Phrase": "Fresh, Simple, Delicious.",
            "Group": "a part of the DRG Family",
            "Menu-Item-1": "Puttanesca",
            "Menu-Item-2": "Cacciatore",
            "Menu-Item-3": "Lasagna",
            "Menu-Item-4": "Fra diavolo",
            "Menu-Item-1-price": 16.99,
            "Menu-Item-2-price": 15.99,
            "Menu-Item-3-price": 12.99,
            "Menu-Item-4-price": 13.99,
            "Menu-Item-1-description": "anchovies, olives, tomatoes, ond other savory items combined into a beautiful sauce served atop fresh spaghetti.",
            "Menu-Item-2-description": "Braised chicken in a tomato and bellpepper sauce, served atop your choice of fresh noodles or without",
            "Menu-Item-3-description": "Layered meat, tomato based sauce, and your choice of bechamel or ricotta layered inbetween.",
            "Menu-Item-4-description": "Spicy and hearty tomato based sauce. Served with your choice of fresh noodles and meat."
        },
        {
            "Restaurant": "Uncle Sam's Steakhouse",
            "Restaurant-Mission": "To perfect the dark arts of mesquite",
            "Brand-Phrase": "Death, Taxes, Steak; and we have the steak.",
            "Group": "a part of the DRG Family",
            "Menu-Item-1": "Ribeye",
            "Menu-Item-2": "Tomahawk",
            "Menu-Item-3": "TX Strip",
            "Menu-Item-4": "Honey Butter Roll",
            "Menu-Item-1-price": 26.99,
            "Menu-Item-2-price": 35.99,
            "Menu-Item-3-price": 25.99,
            "Menu-Item-4-price": 0.50,
            "Menu-Item-1-description": "A beautiful 12oz Ribeye cooked to perfection over mesquite.",
            "Menu-Item-2-description": "A return to a simpler, more cavelike time. 20 oz of meat on a bone grilled on mesquite.",
            "Menu-Item-3-description": "12 oz of TX strip, not NY, this one is grilled on mesquite.",
            "Menu-Item-4-description": "Warm honey-cinna-buttered rolls made fresh, the real reason you're here. Cooked in a mesquite powered oven."
        }
    ]
}